ether_gas_price_server.py
ether_gas_price_server-0.1.4.dist-info/licenses/LICENSE
ether_gas_price_server-0.1.4.dist-info/METADATA
ether_gas_price_server-0.1.4.dist-info/WHEEL
ether_gas_price_server-0.1.4.dist-info/top_level.txt
ether_gas_price_server-0.1.4.dist-info/RECORD
