Metadata-Version: 2.4
Name: ether-gas-price-server
Version: 0.1.4
Summary: Add your description here
Requires-Python: >=3.12
License-File: LICENSE
Requires-Dist: flask>=3.1.0
Dynamic: license-file
